{
  "$schema": "../../schemas/task-status.schema.json",
  "task_id": "AUTOMATION-001",
  "description": "Continuous AI Agent Coordination System",
  "owner": "AI Specialist",
  "status": "PLANNED",
  "sprint": "sprint-0",
  "phase": "phase-5-completion",
  "stream": null,
  "dependencies": [
    "AI-SETUP-001",
    "AI-SETUP-002",
    "ENV-005-AI",
    "ENV-008-AI",
    "ENV-010-AI"
  ],
  "dependencies_resolved": [],
  "started_at": null,
  "completed_at": null,
  "target_duration_minutes": 180,
  "actual_duration_minutes": null,
  "kpis": {
    "automated_task_routing": {
      "target": true,
      "actual": null,
      "unit": "boolean"
    },
    "pr_ci_status_surfaced": {
      "target": true,
      "actual": null,
      "unit": "boolean"
    },
    "incident_alerts_configured": {
      "target": true,
      "actual": null,
      "unit": "boolean"
    }
  },
  "artifacts": [],
  "validations": [],
  "blockers": []
}