{
  "$schema": "../../../schemas/task-status.schema.json",
  "task_id": "ENV-010-AI",
  "description": "Automated Test Generation and Automation",
  "owner": "QA Lead + AI Testing Suite",
  "status": "IN_PROGRESS",
  "sprint": "sprint-0",
  "phase": "phase-3-dependencies",
  "stream": null,
  "dependencies": [
    "ENV-007-AI",
    "ENV-009-AI"
  ],
  "dependencies_resolved": [],
  "started_at": null,
  "completed_at": null,
  "target_duration_minutes": 1,
  "actual_duration_minutes": null,
  "kpis": {
    "coverage": {
      "target": 95,
      "actual": null,
      "unit": "percent"
    },
    "test_generation_time": {
      "target": 1,
      "actual": null,
      "unit": "minutes"
    },
    "ai_verified_scenarios": {
      "target": true,
      "actual": null,
      "unit": "boolean"
    }
  },
  "artifacts": [],
  "validations": [],
  "blockers": []
}