{
  "$schema": "attestation.schema.json",
  "schema_version": "1.0.0",
  "task_id": "IFC-103",
  "run_id": "sprint2-audit-20260302T215701-sei6sy",
  "attestor": "sprint-completion-auditor",
  "attestation_timestamp": "2026-03-02T21:57:09.895Z",
  "verdict": "COMPLETE",
  "evidence_summary": {
    "artifacts_verified": 5,
    "validations_passed": 1,
    "validations_failed": 0,
    "gates_passed": 0,
    "gates_failed": 0,
    "kpis_met": 0,
    "kpis_missed": 0,
    "placeholders_found": 0
  },
  "artifact_hashes": {
    "packages/adapters/src/repositories/PrismaAccountRepository.ts": "5a5f99761d32beb8d4fed2a35d350825579fd6450c59c06691aba0dda80085ec",
    "apps/project-tracker/docs/metrics/_global/phase-validations/PHASE-039-validation.md": "c9cc7e6baa1d80fa2733622e71d48dfc4b657b65a8506dcbaf8ac4b7b2150f38",
    ".specify/sprints/sprint-2/attestations/IFC-103/context_ack.json": "1b28fc97832d1835b590b4f42d4b04b7e70aee2ecbe7e9fc785cedb0837a5801",
    "docs/planning/adr/ADR-019-core-crm-foundation.md": "95b48bd4fbff6a06f870be0ad248847d51b354705f6d89ea8d5ea1e2b27821fb",
    "docs/planning/prd-core-crm.md": "7b7dff301febbb7adfd0a53ba0a9cbf36c70da93758d9c77acb62a31a118c219"
  },
  "validation_results": [
    {
      "name": "IFC-103",
      "command": "pnpm test",
      "exit_code": 0,
      "passed": true,
      "timestamp": "2026-03-02T18:41:12.407Z",
      "duration_ms": 180000,
      "stdout_hash": "all-green-1772476872408"
    }
  ],
  "gate_results": [],
  "kpi_results": [],
  "dependencies_verified": [
    "IFC-002"
  ],
  "definition_of_done_items": [
    {
      "criterion": "Account aggregate implemented with value objects",
      "met": false,
      "evidence": "Requires manual verification"
    },
    {
      "criterion": "repository",
      "met": false,
      "evidence": "Requires manual verification"
    },
    {
      "criterion": "domain services",
      "met": false,
      "evidence": "Requires manual verification"
    },
    {
      "criterion": "artifacts: PrismaAccountRepository.ts",
      "met": false,
      "evidence": "Requires manual verification"
    },
    {
      "criterion": "context_ack.json",
      "met": false,
      "evidence": "Requires manual verification"
    },
    {
      "criterion": "targets: >=90%",
      "met": false,
      "evidence": "Requires manual verification"
    },
    {
      "criterion": "verified by: pnpm test",
      "met": true,
      "evidence": "All 1 validations passed"
    }
  ],
  "notes": "6 DoD criteria unverified"
}