{
  "task_id": "IFC-031",
  "sprint": 17,
  "verdict": "FAIL",
  "timestamp": "2026-04-13T02:10:00Z",
  "reopened_at": "2026-04-13T02:10:00Z",
  "reopened_reason": "User rejected 2026-04-12 COMPLETE verdict after live walkthrough surfaced 7 defects (not reachable, shared-component gaps, DnD broken, React Flow attribution visible, no custom-node registry, toolbar not wired, no CRM-aware node configs). New execution plan at .specify/sprints/sprint-17/planning/IFC-031-plan.md (v2). Spec addendum appended to .specify/sprints/sprint-17/specifications/IFC-031-spec.md. Follow-up IFC-031-FU-002 tracks the re-open.",
  "artifact_hashes": {},
  "dependencies_verified": [
    {
      "id": "IFC-028",
      "status": "Completed",
      "verified": true
    }
  ],
  "validation_results": [
    {
      "name": "TypeScript",
      "command": "pnpm --filter @intelliflow/web typecheck",
      "exit_code": 1,
      "passed": false,
      "timestamp": "2026-04-13T02:10:00Z",
      "stdout_hash": "pending_rerun_after_phase_F"
    },
    {
      "name": "Tests",
      "command": "pnpm --dir apps/web exec vitest run src/components/workflows/__tests__ src/hooks/__tests__/useWorkflowCanvas.test.ts src/hooks/__tests__/useWorkflowMutations.test.ts src/lib/workflow-builder/__tests__",
      "exit_code": 0,
      "passed": false,
      "timestamp": "2026-04-13T02:10:00Z",
      "stdout_hash": "tests_pass_but_feature_broken_runtime_not_validated_against_new_AC"
    },
    {
      "name": "Lint",
      "command": "pnpm --filter @intelliflow/web lint",
      "exit_code": 0,
      "passed": false,
      "timestamp": "2026-04-13T02:10:00Z",
      "stdout_hash": "pending_rerun_after_phase_F"
    },
    {
      "name": "Build",
      "command": "pnpm --filter @intelliflow/web build",
      "exit_code": 0,
      "passed": false,
      "timestamp": "2026-04-13T02:10:00Z",
      "stdout_hash": "pending_rerun_after_phase_F"
    }
  ],
  "evidence_summary": {
    "status": "pending_phase_F",
    "note": "Coverage and runtime_smoke will be regenerated after v2 plan completes. Until then this attestation is explicitly FAIL."
  },
  "notes": "This attestation is in FAIL state during v2 re-execution. The 2026-04-12 PASS is preserved verbatim under historical_passes[0] for audit. DO NOT flip verdict back to COMPLETE until every box in plan §3 A–F is checked AND the user has reviewed the live walkthrough produced in Phase F.",
  "historical_passes": [
    {
      "passed_at": "2026-04-13T00:45:00Z",
      "passed_verdict": "COMPLETE",
      "retracted_at": "2026-04-13T02:10:00Z",
      "retracted_by": "user",
      "retraction_reason": "7 user-visible defects present despite all 4 static validation gates showing PASS. See plan v2 §1.",
      "preserved_snapshot": {
        "timestamp": "2026-04-13T00:45:00Z",
        "verdict": "COMPLETE",
        "validation_results": [
          { "name": "TypeScript", "exit_code": 1, "passed": false, "note": "one pre-existing TS2589 in contacts/[id]/edit/page.tsx:83" },
          { "name": "Tests", "exit_code": 0, "passed": true, "note": "11 files 142 tests" },
          { "name": "Lint", "exit_code": 0, "passed": true, "note": "0 errors 54 warnings pre-existing" },
          { "name": "Build", "exit_code": 0, "passed": true, "note": "compiled in 56s" }
        ],
        "artifact_hashes_at_retract": {
          "apps/web/src/components/workflows/__tests__/WorkflowBuilder.test.tsx": "a50740aaa2af5e09e274a99aacf16f21c5aa43dc9c4142d641f26a4b8f37e5e6",
          "apps/web/src/components/workflows/__tests__/WorkflowToolbar.test.tsx": "6f56002931b241cec65493da56cb0c2cee404bd3746ab88f693233d45666a9c1",
          "apps/web/src/components/workflows/__tests__/WorkflowNodeCard.test.tsx": "6ca3490d6cffca748e0d3a52ad018d6fea9c7ad3af1d726b5d9bf30bdd05486b",
          "apps/web/src/components/workflows/__tests__/ReactFlowComponent.test.tsx": "4e822da2c5c1e419475b4d3aad5672b1340fe48fe0a126e8615bc5456b67dbf0",
          "apps/web/src/hooks/__tests__/useWorkflowCanvas.test.ts": "46a086ed72597f29c892ce2d0edbfcaa4e99c761872ec1825fd699fc6a84a3a4",
          "apps/web/src/hooks/__tests__/useWorkflowMutations.test.ts": "a1adfa5b6fedb8f71951cfa2b0d6b5505ac206bd046f42b4cd233016631fcf7e",
          "apps/web/package.json": "6d9511f44f90036c6fa8bdc135a0383681300fc24bc9f508fff9da3b53f18f76",
          "apps/web/src/components/workflows/ReactFlowComponent.tsx": "27d63c5417f26cf9fe1b356f63b12612f72cb152c55d920703edeb831d459867",
          "apps/web/src/hooks/useWorkflowCanvas.ts": "07621b39affd004d1a324b7c35a6c6d3b074c057a8c915f5f0d39a1457152272",
          "artifacts/misc/usability-test-video.mp4": "dc1bde05977275a617cdec53b8a1e0280b83f6f2f35f16c495e735d75ff78345"
        }
      }
    }
  ]
}
